fitlog/__init__.py
fitlog/__main__.py
fitlog/fastcmd/__init__.py
fitlog/fastcmd/init_cmd.py
fitlog/fastcmd/list_cmd.py
fitlog/fastcmd/log_cmd.py
fitlog/fastcmd/revert_cmd.py
fitlog/fastgit/__init__.py
fitlog/fastgit/committer.py
fitlog/fastlog/__init__.py
fitlog/fastlog/log_read.py
fitlog/fastlog/logger.py
fitlog/fastlog/utils.py
fitlog/fastserver/__init__.py
fitlog/fastserver/app.py
fitlog/fastserver/chart_app.py
fitlog/fastserver/folder_app.py
fitlog/fastserver/line_app.py
fitlog/fastserver/multi_char_app.py
fitlog/fastserver/summary_app.py
fitlog/fastserver/table_app.py
fitlog/fastserver/server/__init__.py
fitlog/fastserver/server/app_utils.py
fitlog/fastserver/server/chart_utils.py
fitlog/fastserver/server/data_container.py
fitlog/fastserver/server/folder_utils.py
fitlog/fastserver/server/log_config_parser.py
fitlog/fastserver/server/server_config.py
fitlog/fastserver/server/summary_utils.py
fitlog/fastserver/server/table_utils.py
fitlog/fastserver/server/utils.py
fitlog/fastserver/static/css/bootstrap-editable.css
fitlog/fastserver/static/css/bootstrap-slider.css
fitlog/fastserver/static/css/bootstrap-table-filter-control.css
fitlog/fastserver/static/css/bootstrap-table-reorder-rows.css
fitlog/fastserver/static/css/bootstrap-table.css
fitlog/fastserver/static/css/bootstrap-table.min.css
fitlog/fastserver/static/css/bootstrap-theme.css
fitlog/fastserver/static/css/bootstrap-theme.css.map
fitlog/fastserver/static/css/bootstrap-theme.min.css
fitlog/fastserver/static/css/bootstrap-theme.min.css.map
fitlog/fastserver/static/css/bootstrap.css
fitlog/fastserver/static/css/bootstrap.css.map
fitlog/fastserver/static/css/bootstrap.min.css
fitlog/fastserver/static/css/bootstrap.min.css.map
fitlog/fastserver/static/css/table.css
fitlog/fastserver/static/fonts/glyphicons-halflings-regular.eot
fitlog/fastserver/static/fonts/glyphicons-halflings-regular.svg
fitlog/fastserver/static/fonts/glyphicons-halflings-regular.ttf
fitlog-0.9.14.dist-info/LICENSE
fitlog-0.9.14.dist-info/METADATA
fitlog-0.9.14.dist-info/WHEEL
fitlog-0.9.14.dist-info/entry_points.txt
fitlog-0.9.14.dist-info/top_level.txt
fitlog-0.9.14.dist-info/RECORD
