Metadata-Version: 2.1
Name: fitlog
Version: 0.9.14
Summary: fitlog: Log tool for Deep Learning, developed by Fudan FastNLP Team
Home-page: UNKNOWN
License: Apache license
Platform: UNKNOWN
Requires-Python: >=3.7
Requires-Dist: docopt (>=0.6.2)
Requires-Dist: flask (>=1.0.2)
Requires-Dist: numpy (>=1.16.4)
Requires-Dist: gitpython (>=3.1.2)
